proxy_provider/__init__.py
proxy_provider/cli/__init__.py
proxy_provider/db/__init__.py
proxy_provider/db/csv_store.py
proxy_provider/db/proxies.csv
proxy_provider/health_check/__init__.py
proxy_provider/scrapers/__init__.py
proxy_provider/utils/__init__.py
proxy_provider/utils/logging.py
proxy_provider-0.1.1.dist-info/LICENSE
proxy_provider-0.1.1.dist-info/METADATA
proxy_provider-0.1.1.dist-info/WHEEL
proxy_provider-0.1.1.dist-info/entry_points.txt
proxy_provider-0.1.1.dist-info/RECORD
