Metadata-Version: 2.1
Name: proxy-provider
Version: 0.1.1
Summary: 
Author: Hector Soria
Author-email: attosoria@hotmail.com
Requires-Python: >=3.9,<4.0
Classifier: Programming Language :: Python :: 3
Classifier: Programming Language :: Python :: 3.9
Classifier: Programming Language :: Python :: 3.10
Classifier: Programming Language :: Python :: 3.11
Classifier: Programming Language :: Python :: 3.12
Requires-Dist: beautifulsoup4 (>=4.13.4,<5.0.0)
Requires-Dist: colorlog (>=6.9.0,<7.0.0)
Requires-Dist: httpx (>=0.28.1,<0.29.0)
Requires-Dist: tqdm (>=4.67.1,<5.0.0)
